jupygit/GitHandlers.py
jupygit/__init__.py
jupygit/gitignore_manipulator.py
jupygit/nb_manipulator.py
jupygit/static/index.js
jupygit-0.4.0.dist-info/LICENSE
jupygit-0.4.0.dist-info/METADATA
jupygit-0.4.0.dist-info/WHEEL
jupygit-0.4.0.dist-info/top_level.txt
jupygit-0.4.0.dist-info/RECORD
