Metadata-Version: 2.1
Name: jupygit
Version: 0.4.0
Summary: Prepare your Notebooks to be pushed to Git
Home-page: https://github.com/fferegrino/jupygit
Author: Antonio Feregrino
Author-email: antonio.feregrino@gmail.com
License: UNKNOWN
Platform: UNKNOWN
